va_shared/__init__.py
va_shared/version.py
va_shared/__pycache__/__init__.cpython-313.pyc
va_shared/__pycache__/version.cpython-313.pyc
va_shared/context/__init__.py
va_shared/context/context_manager.py
va_shared/context/enums.py
va_shared/context/__pycache__/__init__.cpython-313.pyc
va_shared/context/__pycache__/context_manager.cpython-313.pyc
va_shared/context/__pycache__/enums.cpython-313.pyc
va_shared/metrics/__init__.py
va_shared/metrics/path_mapping.py
va_shared/metrics/pipeline_metrics.py
va_shared/metrics/__pycache__/__init__.cpython-313.pyc
va_shared/metrics/__pycache__/path_mapping.cpython-313.pyc
va_shared/metrics/__pycache__/pipeline_metrics.cpython-313.pyc
va_shared/models/__init__.py
va_shared/models/pipeline_io.py
va_shared/models/request_io.py
va_shared/models/__pycache__/__init__.cpython-313.pyc
va_shared/models/__pycache__/pipeline_io.cpython-313.pyc
va_shared/models/__pycache__/request_io.cpython-313.pyc
va_shared/utils/__init__.py
va_shared/utils/logger.py
va_shared/utils/__pycache__/__init__.cpython-313.pyc
va_shared/utils/__pycache__/logger.cpython-313.pyc
va_shared-0.1.23.dist-info/METADATA
va_shared-0.1.23.dist-info/WHEEL
va_shared-0.1.23.dist-info/entry_points.txt
va_shared-0.1.23.dist-info/top_level.txt
va_shared-0.1.23.dist-info/RECORD
