Metadata-Version: 2.2
Name: va-shared
Version: 0.1.23
Summary: Shared utilities for Ensi AI Voice Assistant
Home-page: https://github.com/Solace-smart/ensi-ai-voice-assistant-shared
Author: Solace Smart
License: MIT
Requires-Python: >=3.10
Requires-Dist: pydantic>=2.0.0
Requires-Dist: firebase-admin>=6.0.0
Requires-Dist: aiohttp>=3.8.0
Requires-Dist: ulid-py>=1.1.0
Dynamic: author
Dynamic: home-page
Dynamic: requires-python
